LICENSE
MANIFEST.in
README.md
setup.py
phdseeker/__init__.py
phdseeker/__main__.py
phdseeker/constants.py
phdseeker/main.py
phdseeker/phdseeker_cli.py
phdseeker/repo.yaml
phdseeker/rich_dataframe.py
phdseeker.egg-info/PKG-INFO
phdseeker.egg-info/SOURCES.txt
phdseeker.egg-info/dependency_links.txt
phdseeker.egg-info/entry_points.txt
phdseeker.egg-info/requires.txt
phdseeker.egg-info/top_level.txt