Metadata-Version: 2.1
Name: phdseeker
Version: 0.5.2
Summary: PhD Seeker is a python web scraper to search for fully funded doctorate positions, advertised on well-known academic position websites.
Home-page: https://github.com/Aghababaei/PhD-Seeker
Author: Amin Aghababaei, Javad Razavian, Ana Paula Gomes
Author-email: amin.aghababaei@outlook.com, javadr@gmail.com
Maintainer: Javad Razavian
Maintainer-email: javadr@gmail.com
License: GPLv3
Keywords: Ph.D. Positions,phdseeker,Academia
Requires-Python: >=3.8
License-File: LICENSE
Requires-Dist: brotlipy
Requires-Dist: bs4
Requires-Dist: docopt
Requires-Dist: httpx
Requires-Dist: openpyxl
Requires-Dist: pandas
Requires-Dist: PyYAML
Requires-Dist: rich
Requires-Dist: urllib3
